LICENSE
snakecraft/__init__.py
snakecraft/__main__.py
snakecraft/core.py
snakecraft/exceptions.py
snakecraft/utils.py
snakecraft-0.2.1.dist-info/entry_points.txt
snakecraft-0.2.1.dist-info/LICENSE
snakecraft-0.2.1.dist-info/WHEEL
snakecraft-0.2.1.dist-info/METADATA
snakecraft-0.2.1.dist-info/RECORD
