Metadata-Version: 2.1
Name: snakecraft
Version: 0.2.1
Summary: Describe your Terraform project using Python with inheritance
Home-page: https://github.com/xoraxax/snakecraft
Keywords: terraform,codegeneration
Author: Alexander Schremmer
Author-email: alex@alexanderweb.de
Requires-Python: >=3.6.1,<4.0
Classifier: Development Status :: 4 - Beta
Classifier: Environment :: Console
Classifier: Environment :: Win32 (MS Windows)
Classifier: Intended Audience :: Developers
Classifier: Intended Audience :: System Administrators
Classifier: License :: OSI Approved :: GNU Lesser General Public License v3 or later (LGPLv3+)
Classifier: Operating System :: OS Independent
Classifier: Programming Language :: Other
Classifier: Programming Language :: Python :: 3
Classifier: Programming Language :: Python :: 3 :: Only
Classifier: Programming Language :: Python :: 3.7
Classifier: Programming Language :: Python :: 3.8
Classifier: Programming Language :: Python :: 3.9
Classifier: Topic :: Software Development :: Code Generators
Classifier: Topic :: System :: Networking
Classifier: Topic :: System :: Systems Administration
Requires-Dist: click (>=8.0.1,<9.0.0)
Project-URL: Repository, https://github.com/xoraxax/snakecraft
